{
  "Ankara": [
    {
      "firmaAdi": "DRT BAĞIMSIZ DENETİM VE SERBEST MUHASEBECİ MALİ MÜŞAVİRLİK A.Ş."
    }
  ],
  
  
  "Izmir": [
    {
      "firmaAdi": "A.V.O.D. KURUTULMUŞ GIDA VE TARIM ÜRÜNLERİ SANAYİ TİCARET A.Ş."
    },
    {
      "firmaAdi": "ADRA GAYRİMENKUL YATIRIM ORTAKLIĞI A.Ş."
    }
  ],
  "Istanbul": [
    {
      "firmaAdi": "A1 CAPITAL YATIRIM MENKUL DEĞERLER A.Ş."
    },
    {
      "firmaAdi": "AFYON ÇİMENTO SANAYİ T.A.Ş."
    },
    {
      "firmaAdi": "AG ANADOLU GRUBU HOLDİNG A.Ş."
    },
    {
      "firmaAdi": "AK FİNANSAL KİRALAMA A.Ş."
    },
    {
      "firmaAdi": "AK YATIRIM MENKUL DEĞERLER A.Ş."
    },
    {
      "firmaAdi": "AKÇANSA ÇİMENTO SANAYİ VE TİCARET A.Ş."
    },
    {
      "firmaAdi": "AKÇA KİMYEVİ MADDELER NAKLİYAT TİCARET VE SANAYİ A.Ş."
    },
    {
      "firmaAdi": "AKDENİZ FAKTORİNG A.Ş."
    },
    {
      "firmaAdi": "AKDENİZ YATIRIM HOLDİNG A.Ş."
    },
    {
      "firmaAdi": "AKFEN GAYRİMENKUL YATIRIM ORTAKLIĞI A.Ş."
    },
    {
      "firmaAdi": "AKFEN İŞLETMECİLİK VE TİCARET A.Ş."
    },
    {
      "firmaAdi": "AKFEN MÜHENDİSLİK VE MÜŞAVİRLİK A.Ş."
    },
    {
      "firmaAdi": "AKFEN RENEWABLE ENERGY A.Ş."
    },
    {
      "firmaAdi": "AKFEN SİGORTA A.Ş."
    },
    {
      "firmaAdi": "AKFEN TEKNİK HİZMETLER VE TİCARET A.Ş."
    },
    {
      "firmaAdi": "AKFEN VENTURES A.Ş."
    },
    {
      "firmaAdi": "AKFEN YENİLENEBİLİR ENERJİ A.Ş."
    },
    {
      "firmaAdi": "AKFEN YENİLENEBİLİR ENERJİ YATIRIMLARI A.Ş."
    },
    {
      "firmaAdi": "AKFEN YOL YATIRIM A.Ş."
    },
    {
      "firmaAdi": "AKFEN İNŞAAT VE TİCARET A.Ş."
    },
    {
      "firmaAdi": "AKFEN GAYRİMENKUL GELİŞTİRME VE YATIRIM A.Ş."
    },
    {
      "firmaAdi": "AKFEN HOLDİNG A.Ş."
    },
    {
      "firmaAdi": "AKFEN PORTFÖY YÖNETİMİ A.Ş."
    },
    {
      "firmaAdi": "AKFEN REIT"
    },
    {
      "firmaAdi": "AKFEN SİSTEM TEKNOLOJİLERİ A.Ş."
    },
    {
      "firmaAdi": "AKFEN TOWER GAYRİMENKUL YATIRIM ORTAKLIĞI A.Ş."
    },
    {
      "firmaAdi": "AKFEN VENTURES GAYRİMENKUL YATIRIM ORTAKLIĞI A.Ş."
    },
    {
      "firmaAdi": "AKFEN YATIRIM ORTAKLIĞI A.Ş."
    },
    {
      "firmaAdi": "AKFEN YENİLENEBİLİR ENERJİ YATIRIMLARI GAYRİMENKUL YATIRIM ORTAKLIĞI A.Ş."
    },
    {
      "firmaAdi": "AKFEN YOL YATIRIM GAYRİMENKUL YATIRIM ORTAKLIĞI A.Ş."
    },
    {
      "firmaAdi": "AKG GIDA SANAYİ VE TİCARET A.Ş."
    },
    {
      "firmaAdi": "AKGÜN İNŞAAT TAAHHÜT VE TİCARET A.Ş."
    },
    {
      "firmaAdi": "AKKÖK HOLDİNG A.Ş."
    },
    {
      "firmaAdi": "AKKÖK SANAYİ YATIRIMLARI A.Ş."
    },
    {
      "firmaAdi": "AKKÖK TARIM HAYVANCILIK VE GIDA SANAYİ A.Ş."
    },
    {
      "firmaAdi": "AKKÖK YATIRIM A.Ş."
    },
    {
      "firmaAdi": "AKKÖK YENİLENEBİLİR ENERJİ A.Ş."
    },
    {
      "firmaAdi": "AKKÖK YENİLENEBİLİR ENERJİ YATIRIMLARI A.Ş."
    },
    {
      "firmaAdi": "AKKÖK YOL YATIRIM A.Ş."
    },
    {
      "firmaAdi": "AKKÖK YOL YATIRIM GAYRİMENKUL YATIRIM ORTAKLIĞI A.Ş."
    },
    {
      "firmaAdi": "AKKÖK YÖNETİM HİZMETLERİ A.Ş."
    },
    {
      "firmaAdi": "AKKÖK ZEYTİNYAĞI SANAYİ VE TİCARET A.Ş."
    },
    {
      "firmaAdi": "AKKÖK ZEYTİNYAĞI TARIM HAYVANCILIK VE GIDA SANAYİ A.Ş."
    },
    {
      "firmaAdi": "AKKÖK ZEYTİNYAĞI YATIRIMLARI A.Ş."
    },
    {
      "firmaAdi": "AKKÖK ZEYTİNYAĞI YATIRIMLARI GAYRİMENKUL YATIRIM ORTAKLIĞI A.Ş."
    },
    {
      "firmaAdi": "AKKÖK ZEYTİNYAĞI YATIRIMLARI TARIM HAYVANCILIK VE GIDA SANAYİ A.Ş."
    },
    {
      "firmaAdi": "AKKÖK ZEYTİNYAĞI YATIRIMLARI YÖNETİM HİZMETLERİ A.Ş."
    },
    {
      "firmaAdi": "AKKÖK ZEYTİNYAĞI YATIRIMLARI ZEYTİNYAĞI SANAYİ VE TİCARET A.Ş."
    },
    {
      "firmaAdi": "AKKÖK ZEYTİNYAĞI YATIRIMLARI ZEYTİNYAĞI TARIM HAYVANCILIK VE GIDA SANAYİ A.Ş."
    },
    {
      "firmaAdi": "AKKÖK ZEYTİNYAĞI YATIRIMLARI ZEYTİNYAĞI YATIRIM A.Ş."
    },
    {
      "firmaAdi": "AKKÖK ZEYTİNYAĞI YATIRIMLARI ZEYTİNYAĞI YATIRIM GAYRİMENKUL YATIRIM ORTAKLIĞI A.Ş."
    },
    {
      "firmaAdi": "AKKÖK ZEYTİNYAĞI YATIRIMLARI ZEYTİNYAĞI YATIRIMLARI YÖNETİM HİZMETLERİ A.Ş."
    },
    {
      "firmaAdi": "AKKÖK ZEYTİNYAĞI YATIRIMLARI ZEYTİNYAĞI ZEYTİNYAĞI SANAYİ VE TİCARET A.Ş."
    },
    {
      "firmaAdi": "AKKÖK ZEYTİNYAĞI YATIRIMLARI ZEYTİNYAĞI ZEYTİNYAĞI TARIM HAYVANCILIK VE GIDA SANAYİ A.Ş."
    },
    {
      "firmaAdi": "AKKÖK ZEYTİNYAĞI YATIRIMLARI ZEYTİNYAĞI ZEYTİNYAĞI YATIRIM A.Ş."
    },
    {
      "firmaAdi": "ZORLU FAKTORİNG A.Ş."
    },
    {
      "firmaAdi": "ZKB VARLIK KİRALAMA A.Ş."
    },
    {
      "firmaAdi": "ZİRAAT KATILIM VARLIK KİRALAMA A.Ş. "
    },
    {
      "firmaAdi": "ZİRAAT GAYRİMENKUL YATIRIM ORTAKLIĞI A.Ş."
    },
    {
      "firmaAdi": "YÜNSA YÜNLÜ SANAYİ VE TİCARET A.Ş. "
    },
    {
      "firmaAdi": "YÜKSELEN ÇELİK A.Ş."
    },
    {
      "firmaAdi": "YEŞİL YATIRIM HOLDİNG A.Ş. "
    },
    {
      "firmaAdi": "YEŞİL YAPI ENDÜSTRİSİ A.Ş"
    },
    {
      "firmaAdi": "YEŞİL GAYRİMENKUL YATIRIM ORTAKLIĞI A.Ş."
    },
    {
      "firmaAdi": "YEO TEKNOLOJİ ENERJİ VE ENDÜSTRİ A.Ş."
    },
    {
      "firmaAdi": "YATIRIM VARLIK KİRALAMA A.Ş. "
    },
    {
      "firmaAdi": "YATIRIM FİNANSMAN MENKUL DEĞERLER A.Ş."
    },
    {
      "firmaAdi": "YAPRAK SÜT VE BESİ ÇİFTLİKLERİ SANAYİ VE TİCARET A.Ş. "
    },
    {
      "firmaAdi": "YAPI VE KREDİ BANKASI A.Ş."
    },
    {
      "firmaAdi": "YAPI KREDİ YATIRIM MENKUL DEĞERLER A.Ş."
    },
    {
      "firmaAdi": "YAPI KREDİ FAKTORİNG A.Ş. "
    },
    {
      "firmaAdi": "VOLKSWAGEN DOĞUŞ FİNANSMAN A.Ş. "
    },
    {
      "firmaAdi": "VESTEL ELEKTRONİK SANAYİ VE TİCARET A.Ş."
    },
    {
      "firmaAdi": "VESTEL BEYAZ EŞYA SANAYİ VE TİCARET A.Ş."
    },
    {
      "firmaAdi": "VERUSATURK GİRİŞİM SERMAYESİ YATIRIM ORTAKLIĞI A.Ş. "
    },
    {
      "firmaAdi": "VERUSA HOLDİNG A.Ş."
    },
    {
      "firmaAdi": "VDF FİLO KİRALAMA A.Ş. "
    },
    {
      "firmaAdi": "VBT YAZILIM A.Ş."
    },
    {
      "firmaAdi": "VANET GIDA SANAYİ İÇ VE DIŞ TİCARET A.Ş. "
    },
    {
      "firmaAdi": "VAKKO TEKSTİL VE HAZIR GİYİM SANAYİ İŞLETMELERİ A.Ş. "
    },
    {
      "firmaAdi": "VAKIF VARLIK KİRALAMA A.Ş. "
    },
    {
      "firmaAdi": "VAKIF MENKUL KIYMET YATIRIM ORTAKLIĞI A.Ş. "
    },
    {
      "firmaAdi": "VAKIF GAYRİMENKUL YATIRIM ORTAKLIĞI A.Ş. "
    },
    {
      "firmaAdi": "VAKIF FİNANSAL KİRALAMA A.Ş."
    },
    {
      "firmaAdi": "VAKIF FAKTORİNG A.Ş. "
    },
    {
      "firmaAdi": "ÜNLÜ YATIRIM HOLDİNG A.Ş. "
    },
    {
      "firmaAdi": "ÜNLÜ MENKUL DEĞERLER A.Ş. "
    },
    {
      "firmaAdi": "ÜLKER BİSKÜVİ SANAYİ A.Ş. "
    },
    {
      "firmaAdi": "UZERTAŞ BOYA SANAYİ TİCARET VE YATIRIM A.Ş. "
    },
    {
      "firmaAdi": "ULUSAL FAKTORİNG A.Ş. "
    },
    {
      "firmaAdi": "UFUK YATIRIM YÖNETİM VE GAYRİMENKUL A.Ş. "
    },
    {
      "firmaAdi": "TÜRKİYE VAKIFLAR BANKASI T.A.O. "
    },
    {
      "firmaAdi": "TÜRKİYE ŞİŞE VE CAM FABRİKALARI A.Ş."
    },
    {
      "firmaAdi": "TÜRKİYE SİGORTA A.Ş."
    },
    {
      "firmaAdi": "TÜRKİYE SINAİ KALKINMA BANKASI A.Ş."
    },
    {
      "firmaAdi": "TÜRKİYE KALKINMA VE YATIRIM BANKASI A.Ş."
    },
    {
      "firmaAdi": "TÜRKİYE İŞ BANKASI A.Ş. "
    },
    {
      "firmaAdi": "TÜRKİYE İHRACAT KREDİ BANKASI A.Ş. "
    },
    {
      "firmaAdi": "TÜRKİYE HALK BANKASI A.Ş. "
    },
    {
      "firmaAdi": "TÜRKİYE GARANTİ BANKASI A.Ş. "
    },
    {
      "firmaAdi": "TÜRKER PROJE GAYRİMENKUL VE YATIRIM GELİŞTİRME A.Ş. "
    },
    {
      "firmaAdi": "TÜRK HAVA YOLLARI A.O. "
    },
    {
      "firmaAdi": "TÜPRAŞ-TÜRKİYE PETROL RAFİNERİLERİ A.Ş. "
    },
    {
      "firmaAdi": "TÜMOSAN MOTOR VE TRAKTÖR SANAYİ A.Ş. "
    },
    {
      "firmaAdi": "TURKISH BANK A.Ş. "
    },
    {
      "firmaAdi": "TURKCELL İLETİŞİM HİZMETLERİ A.Ş."
    },
    {
      "firmaAdi": "TURKCELL FİNANSMAN A.Ş. "
    },
    {
      "firmaAdi": "TURK FİNANSMAN A.Ş. "
    },
    {
      "firmaAdi": "TUREKS TURİZM TAŞIMACILIK A.Ş. "
    },
    {
      "firmaAdi": "TURCAS PETROL A.Ş."
    },
    {
      "firmaAdi": "TUĞÇELİK ALÜMİNYUM VE METAL MAMÜLLERİ SANAYİ VE TİCARET A.Ş. "
    },
    {
      "firmaAdi": "TSKB GAYRİMENKUL YATIRIM ORTAKLIĞI A.Ş."
    },
    {
      "firmaAdi": "TRIVE YATIRIM MENKUL DEĞERLER A.Ş. "
    },
    {
      "firmaAdi": "TREND GAYRİMENKUL YATIRIM ORTAKLIĞI A.Ş."
    },
    {
      "firmaAdi": "TORUNLAR GAYRİMENKUL YATIRIM ORTAKLIĞI A.Ş. "
    },
    {
      "firmaAdi": "TOFAŞ TÜRK OTOMOBİL FABRİKASI A.Ş. "
    },
    {
      "firmaAdi": "TİRYAKİ AGRO GIDA SANAYİ VE TİCARET A.Ş"
    },
    {
      "firmaAdi": "TGS DIŞ TİCARET A.Ş. "
    },
    {
      "firmaAdi": "TF VARLIK KİRALAMA A.Ş. "
    },
    {
      "firmaAdi": "TETAMAT GIDA YATIRIMLARI A.Ş."
    },
    {
      "firmaAdi": "TERA YATIRIM MENKUL DEĞERLER A.Ş. "
    },
    {
      "firmaAdi": "TEKNOSA İÇ VE DIŞ TİCARET A.Ş. "
    },
    {
      "firmaAdi": "TEKFEN HOLDİNG A.Ş."
    },
    {
      "firmaAdi": "TEK-ART İNŞAAT TİCARET TURİZM SANAYİ VE YATIRIMLAR A.Ş. "
    },
    {
      "firmaAdi": "TEB FİNANSMAN A.Ş."
    },
    {
      "firmaAdi": "TEB FAKTORİNG A.Ş. "
    },
    {
      "firmaAdi": "TAV HAVALİMANLARI HOLDİNG A.Ş. "
    },
    {
      "firmaAdi": "TATLIPINAR ENERJİ ÜRETİM A.Ş. "
    },
    {
      "firmaAdi": "TAT GIDA SANAYİ A.Ş."
    },
    {
      "firmaAdi": "TAM FİNANS FAKTORİNG A.Ş. "
    },
    {
      "firmaAdi": "TACİRLER YATIRIM MENKUL DEĞERLER A.Ş."
    },
    {
      "firmaAdi": "TAB GIDA SANAYİ VE TİCARET A.Ş. "
    },
    {
      "firmaAdi": "T.C. ZİRAAT BANKASI A.Ş."
    },
    {
      "firmaAdi": "T.C. TOPLU KONUT İDARESİ BAŞKANLIĞI "
    },
    {
      "firmaAdi": "T.C. HAZİNE VE MALİYE BAKANLIĞI DARPHANE VE DAMGA MATBAASI GENEL MÜDÜRLÜĞÜ "
    },
    {
      "firmaAdi": "ŞOK MARKETLER TİCARET A.Ş. "
    },
    {
      "firmaAdi": "ŞEKERBANK T.A.Ş."
    },
    {
      "firmaAdi": "ŞEKER YATIRIM MENKUL DEĞERLER A.Ş."
    },
    {
      "firmaAdi": "ŞEKER GAYRİMENKUL YATIRIM ORTAKLIĞI A.Ş. "
    },
    {
      "firmaAdi": "ŞEKER FİNANSAL KİRALAMA A.Ş."
    },
    {
      "firmaAdi": "SÜMER VARLIK YÖNETİM A.Ş. "
    },
    {
      "firmaAdi": "SÜMER FAKTORİNG A.Ş."
    },
    {
      "firmaAdi": "SUZUKİ MOTORLU ARAÇLAR PAZARLAMA A.Ş. "
    },
    {
      "firmaAdi": "SUWEN TEKSTİL SANAYİ PAZARLAMA A.Ş. "
    },
    {
      "firmaAdi": "SMARTİKS YAZILIM A.Ş. "
    },
    {
      "firmaAdi": "SMART GÜNEŞ ENERJİSİ TEKNOLOJİLERİ ARAŞTIRMA GELİŞTİRME ÜRETİM SANAYİ VE TİCARET A.Ş. "
    },
    {
      "firmaAdi": "SİNPAŞ GAYRİMENKUL YATIRIM ORTAKLIĞI A.Ş."
    },
    {
      "firmaAdi": "SHELL & TURCAS PETROL A.Ş. "
    },
    {
      "firmaAdi": "SETUR SERVİS TURİSTİK A.Ş. "
    },
    {
      "firmaAdi": "SERVET GAYRİMENKUL YATIRIM ORTAKLIĞI A.Ş."
    },
    {
      "firmaAdi": "SENKRON SİBER GÜVENLİK YAZILIM VE BİLİŞİM ÇÖZÜMLERİ A.Ş. "
    },
    {
      "firmaAdi": "SELÇUK ECZA DEPOSU TİCARET VE SANAYİ A.Ş. "
    },
    {
      "firmaAdi": "SEKURO PLASTİK AMBALAJ SANAYİ A.Ş. "
    },
    {
      "firmaAdi": "SARTEN AMBALAJ SANAYİ VE TİCARET A.Ş. "
    },
    {
      "firmaAdi": "SANİCA ISI SANAYİ A.Ş. "
    },
    {
      "firmaAdi": "SAN-EL MÜHENDİSLİK ELEKTRİK TAAHHÜT SANAYİ VE TİCARET A.Ş."
    },
    {
      "firmaAdi": "RUBENİS TEKSTİL SANAYİ TİCARET A.Ş. "
    },
    {
      "firmaAdi": "RODRİGO TEKSTİL SANAYİ VE TİCARET A.Ş. "
    },
    {
      "firmaAdi": "REYSAŞ TAŞIMACILIK VE LOJİSTİK TİCARET A.Ş. "
    },
    {
      "firmaAdi": "REYSAŞ GAYRİMENKUL YATIRIM ORTAKLIĞI A.Ş.  "
    },
    {
      "firmaAdi": " RAY SİGORTA A.Ş. "
    },
    {
      "firmaAdi": "QUICK FİNANSMAN A.Ş. "
    },
    {
      "firmaAdi": "QNB FİNANSBANK A.Ş."
    },
    {
      "firmaAdi": "QNB FİNANS YATIRIM MENKUL DEĞERLER A.Ş.  "
    },
    {
      "firmaAdi": "QNB FİNANS VARLIK KİRALAMA A.Ş.  "
    },
    {
      "firmaAdi": "QNB FİNANS FİNANSAL KİRALAMA A.Ş. "
    },
    {
      "firmaAdi": "QNB FİNANS FAKTORİNG A.Ş."
    },
    {
      "firmaAdi": "PRİZMA PRES MATBAACILIK YAYINCILIK SANAYİ VE TİCARET A.Ş. "
    },
    {
      "firmaAdi": "POLİTEKNİK METAL SANAYİ VE TİCARET A.Ş."
    },
    {
      "firmaAdi": "PLATFORM TURİZM TAŞIMACILIK GIDA İNŞAAT TEMİZLİK HİZMETLERİ SANAYİ VE TİCARET A.Ş. "
    },
    {
      "firmaAdi": "PLASTİKKART AKILLI KART İLETİŞİM SİSTEMLERİ SANAYİ VE TİCARET A.Ş. "
    },
    {
      "firmaAdi": "PHİLLİPCAPİTAL MENKUL DEĞERLER A.Ş. "
    },
    {
      "firmaAdi": "PENTA TEKNOLOJİ ÜRÜNLERİ DAĞITIM TİCARET A.Ş. "
    },
    {
      "firmaAdi": "PEKER GAYRİMENKUL YATIRIM ORTAKLIĞI A.Ş."
    },
    {
      "firmaAdi": "PEGASUS HAVA TAŞIMACILIĞI A.Ş. "
    },
    {
      "firmaAdi": "PC İLETİŞİM VE MEDYA HİZMETLERİ SANAYİ TİCARET A.Ş. "
    },
    {
      "firmaAdi": "PASHA YATIRIM BANKASI A.Ş. "
    },
    {
      "firmaAdi": "PARSAN MAKİNA PARÇALARI SANAYİİ A.Ş. "
    },
    {
      "firmaAdi": "PARK ELEKTRİK ÜRETİM MADENCİLİK SANAYİ VE TİCARET A.Ş. "
    },
    {
      "firmaAdi": "PARDUS GİRİŞİM SERMAYESİ YATIRIM ORTAKLIĞI A.Ş."
    },
    {
      "firmaAdi": "PAMEL YENİLENEBİLİR ELEKTRİK ÜRETİM A.Ş. "
    },
    {
      "firmaAdi": "PALEN ENERJİ DOĞALGAZ DAĞITIM ENDÜSTRİ VE TİCARET A.Ş. "
    },
    {
      "firmaAdi": "ÖZERDEN AMBALAJ SANAYİ A.Ş. "
    },
    {
      "firmaAdi": "ÖZDERİCİ GAYRİMENKUL YATIRIM ORTAKLIĞI A.Ş. "
    },
    {
      "firmaAdi": "ÖZAK GAYRİMENKUL YATIRIM ORTAKLIĞI A.Ş."
    },
    {
      "firmaAdi": "OYAK YATIRIM ORTAKLIĞI A.Ş. "
    },
    {
      "firmaAdi": "OYAK YATIRIM MENKUL DEĞERLER A.Ş. "
    },
    {
      "firmaAdi": "OTTO HOLDİNG A.Ş."
    },
    {
      "firmaAdi": "OTOSOR OTOMOTİV A.Ş."
    },
    {
      "firmaAdi": "OTOKOÇ OTOMOTİV TİCARET VE SANAYİ A.Ş."
    },
    {
      "firmaAdi": "OTOKAR OTOMOTİV VE SAVUNMA SANAYİ A.Ş. "
    },
    {
      "firmaAdi": "OSMANLI YATIRIM MENKUL DEĞERLER A.Ş."
    },
    {
      "firmaAdi": "ORMA ORMAN MAHSULLERİ İNTEGRE SANAYİ VE TİCARET A.Ş. "
    },
    {
      "firmaAdi": "ORGE ENERJİ ELEKTRİK TAAHHÜT A.Ş. "
    },
    {
      "firmaAdi": "ORFİN FİNANSMAN A.Ş."
    },
    {
      "firmaAdi": "OPET PETROLCÜLÜK A.Ş."
    },
    {
      "firmaAdi": "ODAŞ ELEKTRİK ÜRETİM SANAYİ TİCARET A.Ş. "
    },
    {
      "firmaAdi": "OBASE BİLGİSAYAR VE DANIŞMANLIK HİZMETLERİ TİCARET A.Ş"
    },
    {
      "firmaAdi": "NUROL YATIRIM BANKASI A.Ş. "
    },
    {
      "firmaAdi": "NUROL VARLIK KİRALAMA A.Ş. "
    },
    {
      "firmaAdi": "NUROL İNŞAAT VE TİCARET A.Ş. "
    },
    {
      "firmaAdi": "NUROL GAYRİMENKUL YATIRIM ORTAKLIĞI A.Ş. "
    },
    {
      "firmaAdi": "NETAŞ TELEKOMÜNİKASYON A.Ş."
    },
    {
      "firmaAdi": "NET HOLDİNG A.Ş. "
    },
    {
      "firmaAdi": "NATURELGAZ SANAYİ VE TİCARET A.Ş. "
    },
    {
      "firmaAdi": "MOBİLTEL İLETİŞİM HİZMETLERİ SANAYİ VE TİCARET A.Ş. "
    },
    {
      "firmaAdi": "MMC SANAYİ VE TİCARİ YATIRIMLAR A.Ş. "
    },
    {
      "firmaAdi": "MLP SAĞLIK HİZMETLERİ A.Ş."
    },
    {
      "firmaAdi": "MİLPA TİCARİ VE SINAİ ÜRÜNLER PAZARLAMA SANAYİ VE TİCARET A.Ş. "
    },
    {
      "firmaAdi": "MİGROS TİCARET A.Ş. "
    },
    {
      "firmaAdi": "MHR GAYRİMENKUL YATIRIM ORTAKLIĞI A.Ş."
    },
    {
      "firmaAdi": "METRO YATIRIM ORTAKLIĞI A.Ş. "
    },
    {
      "firmaAdi": "METRO TİCARİ VE MALİ YATIRIMLAR HOLDİNG A.Ş."
    },
    {
      "firmaAdi": "METEMTUR YATIRIM ENERJİ TURİZM VE İNŞAAT A.Ş. "
    },
    {
      "firmaAdi": "METAL OTO TİCARET A.Ş."
    },
    {
      "firmaAdi": "MERKO GIDA SANAYİ VE TİCARET A.Ş. "
    },
    {
      "firmaAdi": "MERİT TURİZM YATIRIM VE İŞLETME A.Ş. "
    },
    {
      "firmaAdi": "MERCEDES-BENZ FİNANSMAN TÜRK A.Ş."
    },
    {
      "firmaAdi": "MERCEDES BENZ KAMYON FİNANSMAN A.Ş. "
    },
    {
      "firmaAdi": "MEPET METRO PETROL VE TESİSLERİ SANAYİ TİCARET A.Ş. "
    },
    {
      "firmaAdi": "MEKSA YATIRIM MENKUL DEĞERLER A.Ş. "
    },
    {
      "firmaAdi": "MEGA POLİETİLEN KÖPÜK SANAYİ VE TİCARET A.Ş."
    },
    {
      "firmaAdi": "MAVİ GİYİM SANAYİ VE TİCARET A.Ş. "
    },
    {
      "firmaAdi": "MATRİKS BİLGİ DAĞITIM HİZMETLERİ A.Ş. "
    },
    {
      "firmaAdi": "MARTI OTEL İŞLETMELERİ A.Ş. "
    },
    {
      "firmaAdi": "MARTI GAYRİMENKUL YATIRIM ORTAKLIĞI A.Ş. "
    },
    {
      "firmaAdi": "MARKA YATIRIM HOLDİNG A.Ş. "
    },
    {
      "firmaAdi": "MARKA MAĞAZACILIK A.Ş. "
    },
    {
      "firmaAdi": "MARBAŞ MENKUL DEĞERLER A.Ş. "
    },
    {
      "firmaAdi": "MAKİNA TAKIM ENDÜSTRİSİ A.Ş. "
    },
    {
      "firmaAdi": "MACKOLİK İNTERNET HİZMETLERİ TİCARET A.Ş."
    },
    {
      "firmaAdi": "LİNK BİLGİSAYAR SİSTEMLERİ YAZILIMI VE DONANIMI SANAYİ VE TİCARET A.Ş. "
    },
    {
      "firmaAdi": "LİDER FAKTORİNG A.Ş. "
    },
    {
      "firmaAdi": "LDR TURİZM A.Ş. "
    },
    {
      "firmaAdi": "KUZUGRUP GAYRİMENKUL YATIRIM ORTAKLIĞI A.Ş."
    },
    {
      "firmaAdi": "KUYAŞ YATIRIM A.Ş."
    },
    {
      "firmaAdi": "KUVVA GIDA TİCARET VE SANAYİ YATIRIMLARI A.Ş. "
    },
    {
      "firmaAdi": "KT KİRA SERTİFİKALARI VARLIK KİRALAMA A.Ş. "
    },
    {
      "firmaAdi": "KRON TEKNOLOJİ A.Ş."
    },
    {
      "firmaAdi": "KRİSTAL KOLA VE MEŞRUBAT SANAYİ TİCARET A.Ş. "
    },
    {
      "firmaAdi": "KÖRFEZ GAYRİMENKUL YATIRIM ORTAKLIĞI A.Ş. "
    },
    {
      "firmaAdi": "KOROPLAST TEMİZLİK AMBALAJ ÜRÜNLERİ SANAYİ VE DIŞ TİCARET A.Ş. "
    },
    {
      "firmaAdi": "KORAY GAYRİMENKUL YATIRIM ORTAKLIĞI A.Ş. "
    },
    {
      "firmaAdi": "KONTROLMATİK TEKNOLOJİ ENERJİ VE MÜHENDİSLİK A.Ş."
    },
    {
      "firmaAdi": "KONFRUT GIDA SANAYİ VE TİCARET A.Ş. "
    },
    {
      "firmaAdi": "KOLEKSİYON MOBİLYA SANAYİ A.Ş."
    },
    {
      "firmaAdi": "KOÇ SİSTEM BİLGİ VE İLETİŞİM HİZMETLERİ A.Ş. "
    },
    {
      "firmaAdi": "KOÇ HOLDİNG A.Ş. "
    },
    {
      "firmaAdi": "KOÇ FİNANSMAN A.Ş."
    },
    {
      "firmaAdi": "KOÇ FIAT KREDİ FİNANSMAN A.Ş. "
    },
    {
      "firmaAdi": "KİMTEKS POLİÜRETAN SANAYİ VE TİCARET A.Ş. "
    },
    {
      "firmaAdi": "KİLER HOLDİNG A.Ş. "
    },
    {
      "firmaAdi": "KİLER GAYRİMENKUL YATIRIM ORTAKLIĞI A.Ş. "
    },
    {
      "firmaAdi": "KIZILBÜK GAYRİMENKUL YATIRIM ORTAKLIĞI A.Ş. "
    },
    {
      "firmaAdi": "KERVANSARAY YATIRIM HOLDİNG A.Ş. "
    },
    {
      "firmaAdi": "KERVAN GIDA SANAYİ VE TİCARET A.Ş. "
    },
    {
      "firmaAdi": "KENT FİNANS FAKTORİNG A.Ş. "
    },
    {
      "firmaAdi": "KATILIMEVİM TASARRUF FİNANSMAN A.Ş. "
    },
    {
      "firmaAdi": "KATILIM VARLIK KİRALAMA A.Ş. "
    },
    {
      "firmaAdi": "KARTONSAN KARTON SANAYİ VE TİCARET A.Ş. "
    },
    {
      "firmaAdi": "KARTAL YENİLENEBİLİR ENERJİ ÜRETİM A.Ş."
    },
    {
      "firmaAdi": "KAREL ELEKTRONİK SANAYİ VE TİCARET A.Ş."
    },
    {
      "firmaAdi": "KALKINMA YATIRIM VARLIK KİRALAMA A.Ş. "
    },
    {
      "firmaAdi": "KALESERAMİK ÇANAKKALE KALEBODUR SERAMİK SANAYİ A.Ş. "
    },
    {
      "firmaAdi": "KALEKİM KİMYEVİ MADDELER SANAYİ VE TİCARET A.Ş. "
    },
    {
      "firmaAdi": "KAFEİN YAZILIM HİZMETLERİ TİCARET A.Ş. "
    },
    {
      "firmaAdi": "İZ YATIRIM HOLDİNG A.Ş. "
    },
    {
      "firmaAdi": "İŞ YATIRIM ORTAKLIĞI A.Ş."
    },
    {
      "firmaAdi": "İŞ YATIRIM MENKUL DEĞERLER A.Ş. "
    },
    {
      "firmaAdi": "İŞ GİRİŞİM SERMAYESİ YATIRIM ORTAKLIĞI A.Ş. "
    },
    {
      "firmaAdi": "İŞ GAYRİMENKUL YATIRIM ORTAKLIĞI A.Ş. "
    },
    {
      "firmaAdi": "İŞ FİNANSAL KİRALAMA A.Ş. "
    },
    {
      "firmaAdi": "İŞ FAKTORİNG A.Ş. "
    },
    {
      "firmaAdi": "İNTEMA İNŞAAT VE TESİSAT MALZEMELERİ YATIRIM VE PAZARLAMA A.Ş. "
    },
    {
      "firmaAdi": "İNFO YATIRIM MENKUL DEĞERLER A.Ş. "
    },
    {
      "firmaAdi": "İNDEKS BİLGİSAYAR SİSTEMLERİ MÜHENDİSLİK SANAYİ VE TİCARET A.Ş. "
    },
    {
      "firmaAdi": "İHLAS YAYIN HOLDİNG A.Ş."
    },
    {
      "firmaAdi": "İHLAS HOLDİNG A.Ş. "
    },
    {
      "firmaAdi": "İHLAS HABER AJANSI A.Ş. "
    },
    {
      "firmaAdi": "İHLAS GAZETECİLİK A.Ş. "
    },
    {
      "firmaAdi": "İHLAS GAYRİMENKUL PROJE GELİŞTİRME VE TİCARET A.Ş. "
    },
    {
      "firmaAdi": "İHLAS EV ALETLERİ İMALAT SANAYİ VE TİCARET A.Ş. "
    },
    {
      "firmaAdi": "İDEALİST GAYRİMENKUL YATIRIM ORTAKLIĞI A.Ş. "
    },
    {
      "firmaAdi": "İDEAL FİNANSAL TEKNOLOJİLER VE DANIŞMANLIK A.Ş. "
    },
    {
      "firmaAdi": "IŞIKLAR ENERJİ VE YAPI HOLDİNG A.Ş. "
    },
    {
      "firmaAdi": "IŞIK PLASTİK SANAYİ VE DIŞ TİCARET PAZARLAMA A.Ş. "
    },
    {
      "firmaAdi": "INVESTCO HOLDİNG A.Ş. "
    },
    {
      "firmaAdi": "INVEST AZ YATIRIM MENKUL DEĞERLER A.Ş. "
    },
    {
      "firmaAdi": "INVEO YATIRIM HOLDİNG A.Ş. "
    },
    {
      "firmaAdi": "INGRAM MİCRO BİLİŞİM SİSTEMLERİ A.Ş. "
    },
    {
      "firmaAdi": "ICBC TURKEY BANK A.Ş., "
    }
  ]
}